[{"image": "Screenshot_20.png", "annotations": [{"label": "D-6b", "coordinates": {"x": 357.0, "y": 428.5, "width": 40.0, "height": 35.0}}, {"label": "D-6b", "coordinates": {"x": 844.5, "y": 454.0, "width": 33.0, "height": 38.0}}, {"label": "D-6b", "coordinates": {"x": 20.5, "y": 451.5, "width": 39.0, "height": 33.0}}, {"label": "D-3", "coordinates": {"x": 712.5, "y": 517.0, "width": 21.0, "height": 16.0}}, {"label": "B-36", "coordinates": {"x": 713.5, "y": 494.5, "width": 27.0, "height": 21.0}}]}]